main.py
infotron-0.1.0.dist-info/METADATA
infotron-0.1.0.dist-info/WHEEL
infotron-0.1.0.dist-info/top_level.txt
infotron-0.1.0.dist-info/RECORD
