Metadata-Version: 2.4
Name: infotron
Version: 0.1.0
Summary: personal database manager
Requires-Python: >=3.11
